zencad/__init__.py
zencad/__main__.py
zencad/animate.py
zencad/assemble.py
zencad/axis.py
zencad/bbox.py
zencad/color.py
zencad/curve.py
zencad/geombase.py
zencad/geometry_core_installer.py
zencad/gutil.py
zencad/industrial-robot.svg
zencad/lazifier.py
zencad/opencascade_types.py
zencad/scene.py
zencad/settings.py
zencad/showapi.py
zencad/techpriest.jpg
zencad/util.py
zencad/version.py
zencad/zencad_logo.png
zencad/convert/api.py
zencad/convert/svg.py
zencad/convert/test.svg
zencad/examples/0.Base/csg.py
zencad/examples/0.Base/helloworld.py
zencad/examples/1.GeomPrim/1.prim3d/box.py
zencad/examples/1.GeomPrim/1.prim3d/cone.py
zencad/examples/1.GeomPrim/1.prim3d/cylinder.py
zencad/examples/1.GeomPrim/1.prim3d/halfspace.py
zencad/examples/1.GeomPrim/1.prim3d/platonic.py
zencad/examples/1.GeomPrim/1.prim3d/sphere.py
zencad/examples/1.GeomPrim/1.prim3d/torus.py
zencad/examples/1.GeomPrim/2.prim2d/circle.py
zencad/examples/1.GeomPrim/2.prim2d/ellipse.py
zencad/examples/1.GeomPrim/2.prim2d/fillet_ngon.py
zencad/examples/1.GeomPrim/2.prim2d/interpolate2.py
zencad/examples/1.GeomPrim/2.prim2d/ngon.py
zencad/examples/1.GeomPrim/2.prim2d/polygon.py
zencad/examples/1.GeomPrim/2.prim2d/rectangle.py
zencad/examples/1.GeomPrim/2.prim2d/textshape.py
zencad/examples/1.GeomPrim/2.prim2d/widewire.py
zencad/examples/1.GeomPrim/3.prim1d/bezier.py
zencad/examples/1.GeomPrim/3.prim1d/bspline.py
zencad/examples/1.GeomPrim/3.prim1d/helix.py
zencad/examples/1.GeomPrim/3.prim1d/interpolate.py
zencad/examples/1.GeomPrim/3.prim1d/polysegment.py
zencad/examples/1.GeomPrim/3.prim1d/rounded_polysegment.py
zencad/examples/1.GeomPrim/3.prim1d/segment.py
zencad/examples/2.Operations/boolean.py
zencad/examples/2.Operations/unify.py
zencad/examples/2.Operations/1.AphineTrans/rotate_array.py
zencad/examples/2.Operations/1.AphineTrans/scale.py
zencad/examples/2.Operations/1.AphineTrans/short_rotate.py
zencad/examples/2.Operations/2.Operations/loft.py
zencad/examples/2.Operations/2.Operations/offset.py
zencad-1.3.3.dist-info/LICENSE.txt
zencad-1.3.3.dist-info/METADATA
zencad-1.3.3.dist-info/WHEEL
zencad-1.3.3.dist-info/entry_points.txt
zencad-1.3.3.dist-info/top_level.txt
zencad-1.3.3.dist-info/RECORD
