Metadata-Version: 2.1
Name: zencad
Version: 1.3.3
Summary: CAD system for righteous zen programmers 
Home-page: https://github.com/mirmik/zencad
Author: mirmik
Author-email: mirmikns@yandex.ru
License: MIT
Keywords: testing,cad
Platform: UNKNOWN
Requires-Python: >3.6.0
License-File: LICENSE.txt
Requires-Dist: evalcache (>=1.14.0)
Requires-Dist: numpy
Requires-Dist: pillow
Requires-Dist: psutil
Requires-Dist: requests
Requires-Dist: six
Requires-Dist: zenframe
Provides-Extra: gui
Requires-Dist: PyQt5 ; extra == 'gui'
Requires-Dist: PyQt5-sip ; extra == 'gui'
Requires-Dist: pyopengl ; extra == 'gui'
